[
    {
        "_id": "67f1de22910f3907b8b6c65f",
        "index": 0,
        "imageUrl": "https://science.nasa.gov/wp-content/uploads/2023/06/webb-flickr-52259221868-30e1c78f0c-4k-jpg.webp",
        "title": "Esse aute velit aute proident ipsum cillum eiusmod nisi.",
        "company": "GEEKKO",
        "location": "768 Louisiana Avenue, Westerville, Puerto Rico, 4066",
        "type": "full-time",
        "description": "Ipsum cupidatat magna non irure eiusmod consectetur anim. Esse excepteur enim esse aliqua enim sint irure ut id sunt ea proident laboris exercitation. Elit sit excepteur quis ullamco et ex non et Lorem aliquip enim ea. Ullamco cupidatat aliqua dolor fugiat minim id velit Lorem sit voluptate. Magna dolore excepteur aliquip adipisicing elit excepteur et.\r\n",
        "registered": "2025-01-13T09:04:02 -08:00"
    },
    {
        "_id": "67f1de22e277b19ce211623a",
        "index": 1,
        "imageUrl": "https://science.nasa.gov/wp-content/uploads/2023/06/webb-flickr-52259221868-30e1c78f0c-4k-jpg.webp",
        "title": "Velit dolore pariatur enim in duis consequat enim velit laboris cillum.",
        "company": "ACCEL",
        "location": "501 Clark Street, Rutherford, New York, 8527",
        "type": "full-time",
        "description": "Occaecat ut commodo Lorem duis deserunt. Ipsum exercitation magna voluptate aliqua ad ut cillum pariatur aliquip. Excepteur eiusmod non ad exercitation ad aliquip. Irure quis sunt enim velit.\r\n",
        "registered": "2022-12-03T08:19:49 -08:00"
    },
    {
        "_id": "67f1de225a696a27404c179e",
        "index": 2,
        "imageUrl": "https://science.nasa.gov/wp-content/uploads/2023/06/webb-flickr-52259221868-30e1c78f0c-4k-jpg.webp",
        "title": "Pariatur consectetur id consectetur aute proident elit sit minim anim.",
        "company": "OVIUM",
        "location": "647 Kings Hwy, Advance, Louisiana, 5996",
        "type": "contract",
        "description": "Sunt veniam fugiat deserunt deserunt sit nostrud exercitation amet. Incididunt consequat magna consequat nulla Lorem dolore aliquip consequat excepteur fugiat. Commodo magna cillum sint duis nostrud amet ut et sint commodo magna sunt cupidatat. Aute labore excepteur dolor elit eu voluptate dolor ut elit proident. Esse reprehenderit aliquip voluptate excepteur quis id anim. Duis nostrud in ad mollit incididunt tempor Lorem aute.\r\n",
        "registered": "2023-06-06T03:09:37 -08:00"
    },
    {
        "_id": "67f1de2225d650ac51aeab2a",
        "index": 3,
        "imageUrl": "https://science.nasa.gov/wp-content/uploads/2023/06/webb-flickr-52259221868-30e1c78f0c-4k-jpg.webp",
        "title": "Id adipisicing aute occaecat minim esse ad duis velit laboris.",
        "company": "MULTRON",
        "location": "766 Quincy Street, Belgreen, Vermont, 4141",
        "type": "contract",
        "description": "Anim anim ipsum nisi officia non incididunt dolor cillum pariatur ullamco amet aliqua nisi. Ad est incididunt deserunt exercitation eiusmod officia eiusmod. Sit adipisicing Lorem excepteur officia quis. Nostrud elit fugiat fugiat eu est.\r\n",
        "registered": "2023-02-05T01:06:08 -08:00"
    },
    {
        "_id": "67f1de2257327229ea6b4f19",
        "index": 4,
        "imageUrl": "https://science.nasa.gov/wp-content/uploads/2023/06/webb-flickr-52259221868-30e1c78f0c-4k-jpg.webp",
        "title": "Mollit consectetur eiusmod consequat qui.",
        "company": "COMDOM",
        "location": "487 Glenwood Road, Reinerton, Ohio, 5488",
        "type": "full-time",
        "description": "Sunt sunt anim occaecat ut cupidatat eu consequat laboris ea nostrud. Ipsum eu occaecat amet adipisicing ullamco sint. Qui sunt deserunt anim nisi proident mollit eu in mollit velit.\r\n",
        "registered": "2024-04-06T05:14:43 -08:00"
    },
    {
        "_id": "67f1de2236aaf2a2f255502a",
        "index": 5,
        "imageUrl": "https://science.nasa.gov/wp-content/uploads/2023/06/webb-flickr-52259221868-30e1c78f0c-4k-jpg.webp",
        "title": "Pariatur in eu veniam ex nisi excepteur do et laboris amet elit.",
        "company": "TALKALOT",
        "location": "332 Kent Street, Bath, Massachusetts, 2234",
        "type": "full-time",
        "description": "Labore Lorem nulla irure est ullamco. Nostrud et labore do commodo ipsum ex irure eiusmod est aute qui. Non cupidatat nostrud eu id ea commodo tempor mollit reprehenderit cupidatat velit veniam do. Sunt consequat deserunt laborum cupidatat laborum nulla aliquip nulla. Velit veniam duis magna consequat et ut consectetur velit adipisicing aute. Velit ad est duis magna consectetur.\r\n",
        "registered": "2018-07-19T11:54:36 -08:00"
    }
]